aiohttp_doh.py
aiohttp_doh-0.2.1.dist-info/WHEEL
aiohttp_doh-0.2.1.dist-info/METADATA
aiohttp_doh-0.2.1.dist-info/RECORD
