Metadata-Version: 2.1
Name: aiohttp-doh
Version: 0.2.1
Summary: DNS over HTTPS reslover for aiohttp
Home-page: https://github.com/item4/aiohttp-doh/
License: MIT
Keywords: aiohttp,asyncio,dns,https,security
Author: Kim Jin Su
Author-email: item4_hun@hotmail.com
Requires-Python: >=3.5.3
Classifier: Development Status :: 3 - Alpha
Classifier: License :: OSI Approved :: MIT License
Classifier: Programming Language :: Python :: 3
Classifier: Programming Language :: Python :: 3.6
Classifier: Programming Language :: Python :: 3.7
Requires-Dist: aiohttp (>=3.5,<4.0)
Project-URL: Repository, https://github.com/item4/aiohttp-doh/
